libquery/__init__.py
libquery/base.py
libquery/david_rumsey_map_collection/README.md
libquery/david_rumsey_map_collection/__init__.py
libquery/david_rumsey_map_collection/_fetch_metadata.py
libquery/david_rumsey_map_collection/_querier.py
libquery/david_rumsey_map_collection/_typing.py
libquery/gallica/README.md
libquery/gallica/__init__.py
libquery/gallica/_fetch_metadata.py
libquery/gallica/_querier.py
libquery/gallica/_typing.py
libquery/gallica/_utils.py
libquery/internet_archive/README.md
libquery/internet_archive/__init__.py
libquery/internet_archive/_extract_images.py
libquery/internet_archive/_fetch_file.py
libquery/internet_archive/_fetch_metadata.py
libquery/internet_archive/_querier.py
libquery/internet_archive/_typing.py
libquery/internet_archive/_utils.py
libquery/library_of_congress/README.md
libquery/library_of_congress/__init__.py
libquery/library_of_congress/_fetch_metadata.py
libquery/library_of_congress/_querier.py
libquery/library_of_congress/_typing.py
libquery/typing.py
libquery/utils/image.py
libquery/utils/jsonl.py
libquery/utils/metadata.py
libquery-0.1.2.dist-info/LICENSE
libquery-0.1.2.dist-info/METADATA
libquery-0.1.2.dist-info/WHEEL
libquery-0.1.2.dist-info/RECORD
